landable_parse_tool/__init__.py
landable_parse_tool/business.py
lendable_parsing_tool-1.0.1.dist-info/METADATA
lendable_parsing_tool-1.0.1.dist-info/WHEEL
lendable_parsing_tool-1.0.1.dist-info/entry_points.txt
lendable_parsing_tool-1.0.1.dist-info/top_level.txt
lendable_parsing_tool-1.0.1.dist-info/RECORD
